LICENSE
MANIFEST.in
README.rst
setup.cfg
setup.py
pdnssync/__init__.py
pdnssync/database.py
pdnssync/domain.py
pdnssync/error.py
pdnssync/main.py
pdnssync/parse.py
pdnssync/record.py
pdnssync/utils.py
pdnssync.egg-info/PKG-INFO
pdnssync.egg-info/SOURCES.txt
pdnssync.egg-info/dependency_links.txt
pdnssync.egg-info/entry_points.txt
pdnssync.egg-info/not-zip-safe
pdnssync.egg-info/top_level.txt